pretty_notification_box/__init__.py
pretty_notification_box/frontend/build/asset-manifest.json
pretty_notification_box/frontend/build/bootstrap.min.css
pretty_notification_box/frontend/build/index.html
pretty_notification_box/frontend/build/precache-manifest.063f8dc96c56438ff84e7e8cde75bea3.js
pretty_notification_box/frontend/build/service-worker.js
pretty_notification_box/frontend/build/static/css/main.63c75312.chunk.css
pretty_notification_box/frontend/build/static/css/main.63c75312.chunk.css.map
pretty_notification_box/frontend/build/static/js/2.57a6278a.chunk.js
pretty_notification_box/frontend/build/static/js/2.57a6278a.chunk.js.LICENSE.txt
pretty_notification_box/frontend/build/static/js/2.57a6278a.chunk.js.map
pretty_notification_box/frontend/build/static/js/main.7243fd12.chunk.js
pretty_notification_box/frontend/build/static/js/main.7243fd12.chunk.js.map
pretty_notification_box/frontend/build/static/js/runtime-main.11ec9aca.js
pretty_notification_box/frontend/build/static/js/runtime-main.11ec9aca.js.map
streamlit_pretty_notification_box-0.0.2.dist-info/LICENSE
streamlit_pretty_notification_box-0.0.2.dist-info/METADATA
streamlit_pretty_notification_box-0.0.2.dist-info/WHEEL
streamlit_pretty_notification_box-0.0.2.dist-info/top_level.txt
streamlit_pretty_notification_box-0.0.2.dist-info/RECORD
